openbb_ultima/__init__.py
openbb_ultima/models/__init__.py
openbb_ultima/models/company_news.py
openbb_ultima/py.typed
openbb_ultima/utils/__init__.py
openbb_ultima/utils/helpers.py
openbb_ultima-1.0.0b0.dist-info/WHEEL
openbb_ultima-1.0.0b0.dist-info/entry_points.txt
openbb_ultima-1.0.0b0.dist-info/METADATA
openbb_ultima-1.0.0b0.dist-info/RECORD
