Metadata-Version: 2.1
Name: openbb-ultima
Version: 1.0.0b0
Summary: Ultima Insights extension for OpenBB
Author: Ultima Insights Team
Author-email: hello@ultimainsights.ai
Requires-Python: >=3.8,<4.0
Classifier: Programming Language :: Python :: 3
Classifier: Programming Language :: Python :: 3.8
Classifier: Programming Language :: Python :: 3.9
Classifier: Programming Language :: Python :: 3.10
Classifier: Programming Language :: Python :: 3.11
Requires-Dist: openbb-core (>=1.0.0b0,<2.0.0)
